iverilog/fullAdder.v
module fullAdder(A,B,Cin,Sum,Carry);
output Sum,Carry;
input A, B, Cin;
wire w1,w2,w3,w4;
xor(w1,A,B);
xor(Sum,w1,Cin);

and(w2,A,B);
and(w3,B,Cin);
and(w4,Cin,A);

or(Carry,w2,w3,w4);
endmodule

iverilog/fullAdder_tb.v
module fullAdder_tb;
reg A,B,Cin; 
wire Sum,Carry;
fullAdder circuit5(A,B,Cin,Sum,Carry);
initial
begin
A=1'b0;B=1'b0;Cin=1'b0;  #20;
A=1'b0;B=1'b0;Cin=1'b1;  #20;
A=1'b0;B=1'b1;Cin=1'b0;  #20;
A=1'b0;B=1'b1;Cin=1'b1;  #20;
A=1'b1;B=1'b0;Cin=1'b0;  #20;
A=1'b1;B=1'b0;Cin=1'b1;  #20;
A=1'b1;B=1'b1;Cin=1'b0;  #20;
A=1'b1;B=1'b1;Cin=1'b1;  #20;
end
initial
begin
$monitor($time,"A=%b, B=%b, Cin=%b, Sum=%b, Carry=%b",A,B,Cin,Sum,Carry);
end
initial
begin
$dumpfile("fullAdder.vcd");
$dumpvars(0,fullAdder_tb);
end
endmodule

iverilog/fullAdder.vcd
$date
	Thu Sep 21 22:58:23 2023
$end
$version
	Icarus Verilog
$end
$timescale
	1s
$end
$scope module fullAdder_tb $end
$var wire 1 ! Sum $end
$var wire 1 " Carry $end
$var reg 1 # A $end
$var reg 1 $ B $end
$var reg 1 % Cin $end
$scope module circuit5 $end
$var wire 1 # A $end
$var wire 1 $ B $end
$var wire 1 " Carry $end
$var wire 1 % Cin $end
$var wire 1 ! Sum $end
$var wire 1 & w1 $end
$var wire 1 ' w2 $end
$var wire 1 ( w3 $end
$var wire 1 ) w4 $end
$upscope $end
$upscope $end
$enddefinitions $end
#0
$dumpvars
0)
0(
0'
0&
0%
0$
0#
0"
0!
$end
#20
1!
1%
#40
1&
0%
1$
#60
1"
0!
1(
1%
#80
0"
1!
0(
0%
0$
1#
#100
1"
0!
1)
1%
#120
0)
0&
1'
0%
1$
#140
1!
1(
1)
1%
